perfect_numbers/__init__.py
perfect_number-0.0.3.dist-info/LICENSE.txt
perfect_number-0.0.3.dist-info/METADATA
perfect_number-0.0.3.dist-info/WHEEL
perfect_number-0.0.3.dist-info/top_level.txt
perfect_number-0.0.3.dist-info/RECORD
