Metadata-Version: 2.1
Name: perfect-number
Version: 0.0.3
Summary: MODULE IS USE TO FIND PERFECT NUMBER
Home-page: https://github.com/RETROEAGLE721/perfect_numbers
Download-URL: https://github.com/RETROEAGLE721/perfect_numbers/archive/refs/tags/0.0.1.tar.gz
Author: RETROeagle
Author-email: postviral75@gmail.com
License: MIT
Keywords: CUSTOM,MODULE,PERFECT_NUMBER
Classifier: Development Status :: 3 - Alpha
Classifier: Intended Audience :: Developers
Classifier: Topic :: Software Development :: Build Tools
Classifier: License :: OSI Approved :: MIT License
Classifier: Programming Language :: Python :: 3
Classifier: Programming Language :: Python :: 3.4
Classifier: Programming Language :: Python :: 3.5
Classifier: Programming Language :: Python :: 3.6
Classifier: Programming Language :: Python :: 3.7
Classifier: Programming Language :: Python :: 3.8
Classifier: Programming Language :: Python :: 3.9
Classifier: Programming Language :: Python :: 3.10
Classifier: Programming Language :: Python :: 3.11
License-File: LICENSE.txt
